examples/__init__.py
examples/demo.py
examples/simple_demo.py
md_katex/__init__.py
md_katex/extension.py
tests/__init__.py
tests/test_backtick_pattern.py
tests/test_mdkatex.py
md_katex-0.3.0.dist-info/LICENSE
md_katex-0.3.0.dist-info/METADATA
md_katex-0.3.0.dist-info/WHEEL
md_katex-0.3.0.dist-info/entry_points.txt
md_katex-0.3.0.dist-info/top_level.txt
md_katex-0.3.0.dist-info/RECORD
