Metadata-Version: 2.1
Name: md-katex
Version: 0.3.0
Summary: A Markdown extension for rendering LaTeX math using Katex
Home-page: https://github.com/dbzhang800/md_katex
Author: Debao Zhang
Author-email: hello@debao.me
Classifier: Programming Language :: Python :: 3
Classifier: License :: OSI Approved :: MIT License
Classifier: Operating System :: OS Independent
Requires-Python: >=3.9
License-File: LICENSE
Requires-Dist: markdown >=3.0
